avltree/__init__.py
avltree/_avl_tree.py
avltree/_avl_tree_key.py
avltree/_avl_tree_node.py
avltree-1.1.2.dist-info/LICENSE
avltree-1.1.2.dist-info/METADATA
avltree-1.1.2.dist-info/WHEEL
avltree-1.1.2.dist-info/top_level.txt
avltree-1.1.2.dist-info/RECORD
