Metadata-Version: 2.1
Name: avltree
Version: 1.1.2
Summary: Lightweight, pure-python AVL tree
Author-email: Charles Andrews <cfandrews@outlook.com>
License: MIT License
Project-URL: Homepage, https://github.com/cfandrews/PythonAvlTree
Requires-Python: >=3.8
License-File: LICENSE
Provides-Extra: build
Requires-Dist: pre-commit ==3.5.0 ; extra == 'build'
Requires-Dist: isort ==5.12.0 ; extra == 'build'
Requires-Dist: ruff ==0.1.3 ; extra == 'build'
Requires-Dist: mypy ==1.6.1 ; extra == 'build'
Requires-Dist: pytest ==7.4.3 ; extra == 'build'
Requires-Dist: assertpy ==1.1 ; extra == 'build'
Requires-Dist: pytest-cov ==4.1.0 ; extra == 'build'
Requires-Dist: build ==1.0.3 ; extra == 'build'
Requires-Dist: pdoc ==14.1.0 ; extra == 'build'
